timestamps70/__init__.py
timestamps70/main_func.py
Timestamps70-1.0.1.dist-info/LICENSE
Timestamps70-1.0.1.dist-info/METADATA
Timestamps70-1.0.1.dist-info/WHEEL
Timestamps70-1.0.1.dist-info/top_level.txt
Timestamps70-1.0.1.dist-info/RECORD
