Metadata-Version: 2.1
Name: Timestamps70
Version: 1.0.1
Summary: This package converts timestamps and clocktime to the scale between 1 and 1440
Home-page: UNKNOWN
Author: Jane Smith
Author-email: jamesmith@example.com
License: UNKNOWN
Platform: UNKNOWN
Classifier: Programming Language :: Python :: 3
Classifier: License :: OSI Approved :: MIT License
Classifier: Operating System :: OS Independent
Requires-Python: >=3.6
License-File: LICENSE
